   {
      "@id":"dtmi:sid:Common_Domain:PartyRole;1",
      "@type":"Interface",
      "displayName":"PartyRole",
      "@context":"dtmi:dtdl:context;2",
      "contents":[
         {
            "@type":"Property",
            "name":"ID",
            "schema":"string"
         },
         {
            "@type":"Property",
            "name":"name",
            "schema":"string"
         },
         {
            "@type":"Property",
            "name":"status",
            "schema":"string"
         },
         {
            "@type":"Relationship",
            "name":"PartyRoleInvolvedInCommunicationInteractionRole",
            "target":"dtmi:sid:Common_Domain:CommunicationInteractionRole;1"
         },
         {
            "@type":"Relationship",
            "name":"PartyRoleRequestsFor",
            "target":"dtmi:sid:Common_Domain:MetricMeasurementObservation;1"
         },
         {
            "@type":"Relationship",
            "name":"PartyStabilityMeasuredBy",
            "target":"dtmi:sid:Common_Domain:PartyCreditProfile;1"
         },
         {
            "@type":"Relationship",
            "name":"PartyRoleContactableVia",
            "target":"dtmi:sid:Common_Domain:ContactMedium;1"
         },
         {
            "@type":"Relationship",
            "name":"PartyRolePlays",
            "target":"dtmi:sid:Common_Domain:InvolvementRole;1"
         }
      ]
   }
