   {
      "@id":"dtmi:smartdatamodels:Common_Domain:PartyRole;1",
      "@type":"Interface",
      "displayName":"PartyRole",
      "@context":"dtmi:dtdl:context;2",
      "contents":[
         {
            "@type":"Property",
            "name":"name",
            "schema":"string"
         },
         {
            "@type":"Property",
            "name":"status",
            "schema":"string"
         },
         {
            "@type":"Relationship",
            "name":"PartyRoleInvolvedInCommunicationInteractionRole",
            "target":"dtmi:smartdatamodels:Common_Domain:CommunicationInteractionRole;1"
         }
      ]
   }
