 {
      "@id":"dtmi:sid:Common_Domain:CommunicationInteractionUseCase;1",
      "@type":"Interface",
      "displayName":"CommunicationInteractionUseCase",
      "@context":"dtmi:dtdl:context;2",
      "contents":[
        {
            "@type":"Property",
            "name":"content",
            "schema":"string"
         },
         {
            "@type":"Relationship",
            "name":"CommunicationInteractionUseCaseConcernsInteractionAction",
            "target":"dtmi:sid:Common_Domain:CommunicationInteractionAction;1"
         }
      ]
   }
